{
    "id": 8,
    "english": "grandfather",
    "his_relations": {
        "pa": 29,
        "ma": 30,
        "bo": 9,
        "cm": 28,
        "ko": 26,
        "ti": 27
    },
    "my_relations": [
        {
            "member": 1,
            "relation": "pa"
        },
        {
            "member": 2,
            "relation": "pa"
        }
    ],
    "variants": [
        {
            "hanji": "公",
            "imji": "겅·",
            "tailo": "kong",
            "taiji": "kong1"
        },
        {
            "hanji": "阿公",
            "imji": "아·겅·",
            "tailo": "a-kong",
            "taiji": "ah3kong1"
        },
        {
            "hanji": "裡公",
            "imji": "래-겅·",
            "tailo": "lāi-kong",
            "taiji": "lai33kong1"
        }
    ]
}